qaz008fear/__init__.py
qaz008fear/qaz008fear.py
qaz008fear-0.4.dist-info/METADATA
qaz008fear-0.4.dist-info/WHEEL
qaz008fear-0.4.dist-info/top_level.txt
qaz008fear-0.4.dist-info/RECORD
