Metadata-Version: 2.4
Name: qaz008fear
Version: 0.4
Summary: geoestadistica
Home-page: https://github.com/fededimant/qaz008fear
Author: fede
Author-email: fededimant@hotmail.com
Dynamic: author
Dynamic: author-email
Dynamic: home-page
Dynamic: summary
